[
  {
    "xAxis": {
      "type": "Wajib KTP",
      "region": "Kabupaten",
      "name": "Pandeglang",
      "yyyy": "2017",
      "index": "Pandeglang-2017",
      "data": [
        "(L) WAJIB KTP",
        "(P) WAJIB KTP2"
      ]
    },
    "series": [
      {
        "data": [
          441446,
          415822
        ]
      }
    ]
  },
  {
    "xAxis": {
      "type": "Wajib KTP",
      "region": "Kabupaten",
      "name": "Lebak",
      "yyyy": "2017",
      "index": "Lebak-2017",
      "data": [
        "(L) WAJIB KTP",
        "(P) WAJIB KTP2"
      ]
    },
    "series": [
      {
        "data": [
          459815,
          434611
        ]
      }
    ]
  },
  {
    "xAxis": {
      "type": "Wajib KTP",
      "region": "Kabupaten",
      "name": "Tangerang",
      "yyyy": "2017",
      "index": "Tangerang-2017",
      "data": [
        "(L) WAJIB KTP",
        "(P) WAJIB KTP2"
      ]
    },
    "series": [
      {
        "data": [
            977461,
            947650
        ]
      }
    ]
  },
  {
    "xAxis": {
      "type": "Wajib KTP",
      "region": "Kabupaten",
      "name": "Serang",
      "yyyy": "2017",
      "index": "Serang-2017",
      "data": [
        "(L) WAJIB KTP",
        "(P) WAJIB KTP2"
      ]
    },
    "series": [
      {
        "data": [
            520553,
            499568
        ]
      }
    ]
  },
  {
    "xAxis": {
      "type": "Wajib KTP",
      "region": "Kota",
      "name": "Tangerang",
      "yyyy": "2017",
      "index": "Kota-Tangerang-2017",
      "data": [
        "(L) WAJIB KTP",
        "(P) WAJIB KTP2"
      ]
    },
    "series": [
      {
        "data": [
            609390,
            606687
        ]
      }
    ]
  },
  {
    "xAxis": {
      "type": "Wajib KTP",
      "region": "Kota",
      "name": "Cilegon",
      "yyyy": "2017",
      "index": "Kota-Cilegon-2017",
      "data": [
        "(L) WAJIB KTP",
        "(P) WAJIB KTP2"
      ]
    },
    "series": [
      {
        "data": [
            145082,
            140662
        ]
      }
    ]
  },
  {
    "xAxis": {
      "type": "Wajib KTP",
      "region": "Kota",
      "name": "Serang",
      "yyyy": "2017",
      "index": "Kota-Serang-2017",
      "data": [
        "(L) WAJIB KTP",
        "(P) WAJIB KTP2"
      ]
    },
    "series": [
      {
        "data": [
            221820,
            212125
        ]
      }
    ]
  },
  {
    "xAxis": {
      "type": "Wajib KTP",
      "region": "Kota",
      "name": "Tangerang Selatan",
      "yyyy": "2017",
      "index": "Kota-Tangerang Selatan-2017",
      "data": [
        "(L) WAJIB KTP",
        "(P) WAJIB KTP2"
      ]
    },
    "series": [
      {
        "data": [
          456903,
          459347
        ]
      }
    ]
  }
]
